lilili/__init__.py
lilili/apis/__init__.py
lilili/apis/api.py
lilili/apis/github.py
lilili/apis/npmjs.py
lilili/apis/pypi.py
lilili/apis/rubygems.py
lilili/cli.py
lilili/db/__init__.py
lilili/db/defs.py
lilili/db/helpers.py
lilili/errors.py
lilili/load.py
lilili/search.py
lilili/server.py
lilili/utils.py
lilili-0.1.0.dist-info/entry_points.txt
lilili-0.1.0.dist-info/LICENSE
lilili-0.1.0.dist-info/WHEEL
lilili-0.1.0.dist-info/METADATA
lilili-0.1.0.dist-info/RECORD
