Metadata-Version: 2.1
Name: lilili
Version: 0.1.0
Summary: List the Licenses of the Libraries.
Home-page: https://github.com/poyo46/lilili
License: Apache-2.0
Keywords: software,license,licensed,fossology
Author: poyo46
Author-email: poyo4rock@gmail.com
Requires-Python: >=3.6,<4.0
Classifier: Development Status :: 3 - Alpha
Classifier: Intended Audience :: Developers
Classifier: License :: OSI Approved :: Apache Software License
Classifier: Operating System :: MacOS :: MacOS X
Classifier: Operating System :: POSIX :: Linux
Classifier: Programming Language :: Python :: 3
Classifier: Programming Language :: Python :: 3.6
Classifier: Programming Language :: Python :: 3.7
Classifier: Programming Language :: Python :: 3.8
Classifier: Programming Language :: Python :: 3.9
Requires-Dist: Flask (>=1.1.2,<2.0.0)
Requires-Dist: PyYAML (>=5.4.1,<6.0.0)
Requires-Dist: SQLAlchemy (>=1.3.23,<2.0.0)
Requires-Dist: cleo (>=0.8.1,<0.9.0)
Requires-Dist: requests (>=2.25.1,<3.0.0)
Project-URL: Repository, https://github.com/poyo46/lilili
